{
  "$comment": "Generated from sensor_msgs/TimeReference.msg using https://github.com/foxglove/message-schemas",
  "type": "object",
  "properties": {
    "header": {
      "$comment": "Generated from std_msgs/Header.msg using https://github.com/foxglove/message-schemas",
      "type": "object",
      "properties": {
        "seq": {
          "$comment": "originally uint32",
          "type": "integer"
        },
        "stamp": {
          "$comment": "originally time",
          "type": "object",
          "properties": {
            "sec": {
              "type": "integer"
            },
            "nsec": {
              "type": "integer"
            }
          }
        },
        "frame_id": {
          "type": "string"
        }
      }
    },
    "time_ref": {
      "$comment": "originally time",
      "type": "object",
      "properties": {
        "sec": {
          "type": "integer"
        },
        "nsec": {
          "type": "integer"
        }
      }
    },
    "source": {
      "type": "string"
    }
  }
}
